nbserverproxy/__init__.py
nbserverproxy/handlers.py
nbserverproxy-0.8.8.dist-info/LICENSE
nbserverproxy-0.8.8.dist-info/METADATA
nbserverproxy-0.8.8.dist-info/WHEEL
nbserverproxy-0.8.8.dist-info/top_level.txt
nbserverproxy-0.8.8.dist-info/RECORD
