Metadata-Version: 1.2
Name: nbserverproxy
Version: 0.8.8
Summary: Jupyter server extension to proxy web services
Home-page: https://github.com/jupyterhub/nbserverproxy
Author: Ryan Lovett & Yuvi Panda
Author-email: rylo@berkeley.edu
License: BSD 3-Clause
Platform: UNKNOWN
Classifier: Framework :: Jupyter
Requires-Python: >=3.5
